Workbook

Sheet Escenarios
A1: Costo mensual y anual por cuenta (cliente) — cambia las cantidades en azul
A3: Escenario | B3: Admins (Author Pro) | C3: Usuarios con chat (Reader Pro) | D3: Usuarios solo dashboard (Reader) | E3: Cuota Quick | F3: Licencias | G3: Infra AWS + Cognito | H3: Total mensual | I3: Total anual | J3: % licencias Quick
A4: Piloto (10 con chat) | B4: 1 | C4: 10 | D4: 0 | E4: =Supuestos!$B$4 | F4: =B4*Supuestos!$B$5+C4*Supuestos!$B$6+D4*Supuestos!$B$7 | G4: =Supuestos!$B$19+(B4+C4+D4)*Supuestos!$B$8 | H4: =E4+F4+G4 | I4: =H4*12 | J4: =(E4+F4)/H4
A5: Área comercial (50 con chat) | B5: 1 | C5: 50 | D5: 0 | E5: =Supuestos!$B$4 | F5: =B5*Supuestos!$B$5+C5*Supuestos!$B$6+D5*Supuestos!$B$7 | G5: =Supuestos!$B$19+(B5+C5+D5)*Supuestos!$B$8 | H5: =E5+F5+G5 | I5: =H5*12 | J5: =(E5+F5)/H5
A6: Empresa (100 con chat) | B6: 1 | C6: 100 | D6: 0 | E6: =Supuestos!$B$4 | F6: =B6*Supuestos!$B$5+C6*Supuestos!$B$6+D6*Supuestos!$B$7 | G6: =Supuestos!$B$19+(B6+C6+D6)*Supuestos!$B$8 | H6: =E6+F6+G6 | I6: =H6*12 | J6: =(E6+F6)/H6
A7: Mixto (10 con chat + 90 solo dashboard) | B7: 1 | C7: 10 | D7: 90 | E7: =Supuestos!$B$4 | F7: =B7*Supuestos!$B$5+C7*Supuestos!$B$6+D7*Supuestos!$B$7 | G7: =Supuestos!$B$19+(B7+C7+D7)*Supuestos!$B$8 | H7: =E7+F7+G7 | I7: =H7*12 | J7: =(E7+F7)/H7
A10: Notas
A11: • Precios en USD, región us-east-1, sin impuestos. Fuente: página oficial de precios de Amazon Quick (septiembre 2026).
A12: • La cuota de $250 es por cuenta de AWS: con una cuenta por cliente, se paga una vez por cliente.
A13: • Infraestructura AWS estimada con el uso real de septiembre 2026 (Cost Explorer) más margen.
A14: • No incluye: desarrollo, soporte, dominio propio ni impuestos locales.
A15: • La cuenta de AWS actual comparte gastos con otros proyectos (~$710/mes en DynamoDB, Transfer Family y OpenSearch) que NO son de esta solución.

Sheet Supuestos
A1: Precios unitarios (USD/mes) — editables
A3: Concepto | B3: Precio | C3: Nota
A4: Cuota de infraestructura Quick (por cuenta) | B4: 250 | C4: Fija por cuenta con usuarios Pro o chat habilitado
A5: Author Pro (administrador) | B5: 40 | C5: Mantiene topic, agente y dashboard
A6: Reader Pro (dashboard + chat) | B6: 20 | C6: Por usuario
A7: Reader (solo dashboard) | B7: 3 | C7: Por usuario, sin chat
A8: Cognito Plus por usuario activo (MAU) | B8: 0.02 | C8: Por usuario activo al mes
A10: Infraestructura AWS fija por cuenta (USD/mes)
A11: Servicio | B11: Costo | C11: Base
A12: AWS WAF (1 Web ACL + 4 reglas) | B12: 9 | C12: $5 ACL + $1 por regla; $0.60 por millón de solicitudes
A13: AWS Glue (cargas + barrido diario) | B13: 3 | C13: Real sep-2026: $0.33; margen para más cargas
A14: Amazon Athena | B14: 3 | C14: Real sep-2026: $2.58
A15: CloudWatch logs (90 días) y 11 alarmas | B15: 3.1 | C15: $0.10 por alarma + ingesta de logs
A16: Amazon S3 (datos, web, versiones) | B16: 1 | C16: ~105 MB de datos hoy
A17: AWS KMS (llave del topic de alertas) | B17: 1 | C17: $1 por llave al mes
A18: Lambda, API Gateway, CloudFront, SPICE, X-Ray | B18: 1.9 | C18: Dentro o cerca de la capa gratuita
A19: Total infraestructura AWS | B19: =SUM(B12:B18)
